[{"stat": {"stat_id": "9004003", "value": "193/372"}}, {"stat": {"stat_id": "5", "value": ".519"}}, {"stat": {"stat_id": "9007006", "value": "87/107"}}, {"stat": {"stat_id": "8", "value": ".813"}}, {"stat": {"stat_id": "10", "value": "66"}}, {"stat": {"stat_id": "12", "value": "539"}}, {"stat": {"stat_id": "15", "value": "179"}}, {"stat": {"stat_id": "16", "value": "111"}}, {"stat": {"stat_id": "17", "value": "31"}}, {"stat": {"stat_id": "18", "value": "17"}}, {"stat": {"stat_id": "19", "value": "48"}}]