{"fantasy_content": {"xml:lang": "en-US", "yahoo:uri": "/fantasy/v2/team/402.l.198727.t.7/roster;week=6", "team": [[{"team_key": "402.l.198727.t.7"}, {"team_id": "7"}, {"name": "Luis's Legit Team"}, [], {"url": "https://basketball.fantasysports.yahoo.com/nba/198727/7"}, {"team_logos": [{"team_logo": {"size": "large", "url": "https://s.yimg.com/cv/apiv2/default/nba/nba_7_l.png"}}]}, [], {"waiver_priority": 9}, [], {"number_of_moves": "13"}, {"number_of_trades": "2"}, {"roster_adds": {"coverage_type": "week", "coverage_value": 6, "value": "2"}}, [], {"league_scoring_type": "head"}, [], {"draft_position": 8}, {"has_draft_grade": 0}, [], [], {"managers": [{"manager": {"manager_id": "7", "nickname": "Luis", "guid": "LIODO4H6SUONAEMQXAI52SZOUI", "email": "luisalvaradoan@yahoo.com", "image_url": "https://s.yimg.com/ag/images/default_user_profile_pic_64sq.jpg"}}]}], {"roster": {"coverage_type": "date", "date": "2021-01-27", "is_editable": 0, "0": {"players": {"0": {"player": [[{"player_key": "402.p.5159"}, {"player_id": "5159"}, {"name": {"full": "Kentavious Caldwell-Pope", "first": "Kentavious", "last": "Caldwell-Pope", "ascii_first": "Kentavious", "ascii_last": "Caldwell-Pope"}}, {"editorial_player_key": "nba.p.5159"}, {"editorial_team_key": "nba.t.13"}, {"editorial_team_full_name": "Los Angeles Lakers"}, {"editorial_team_abbr": "LAL"}, {"uniform_number": "1"}, {"display_position": "PG,SG"}, {"headshot": {"url": "https://s.yimg.com/iu/api/res/1.2/kw3M1yTKbTtXrD426dCNSw--~C/YXBwaWQ9eXNwb3J0cztjaD0yMzM2O2NyPTE7Y3c9MTc5MDtkeD04NTc7ZHk9MDtmaT11bGNyb3A7aD02MDtxPTEwMDt3PTQ2/https://s.yimg.com/xe/i/us/sp/v/nba_cutout/players_l/12222020/5159.png", "size": "small"}, "image_url": "https://s.yimg.com/iu/api/res/1.2/kw3M1yTKbTtXrD426dCNSw--~C/YXBwaWQ9eXNwb3J0cztjaD0yMzM2O2NyPTE7Y3c9MTc5MDtkeD04NTc7ZHk9MDtmaT11bGNyb3A7aD02MDtxPTEwMDt3PTQ2/https://s.yimg.com/xe/i/us/sp/v/nba_cutout/players_l/12222020/5159.png"}, {"is_undroppable": "0"}, {"position_type": "P"}, {"primary_position": "PG"}, {"eligible_positions": [{"position": "PG"}, {"position": "SG"}, {"position": "G"}, {"position": "Util"}]}, {"has_player_notes": 1}, [], {"player_notes_last_timestamp": 1611285754}], {"selected_position": [{"coverage_type": "date", "date": "2021-01-27"}, {"position": "PG"}, {"is_flex": 0}]}]}, "1": {"player": [[{"player_key": "402.p.5142"}, {"player_id": "5142"}, {"name": {"full": "Justin Holiday", "first": "Justin", "last": "Holiday", "ascii_first": "Justin", "ascii_last": "Holiday"}}, {"editorial_player_key": "nba.p.5142"}, {"editorial_team_key": "nba.t.11"}, {"editorial_team_full_name": "Indiana Pacers"}, {"editorial_team_abbr": "Ind"}, {"uniform_number": "8"}, {"display_position": "SG,SF"}, {"headshot": {"url": "https://s.yimg.com/iu/api/res/1.2/x4A6nosUX0Ueltqb9UXvRQ--~C/YXBwaWQ9eXNwb3J0cztjaD0yMzM2O2NyPTE7Y3c9MTc5MDtkeD04NTc7ZHk9MDtmaT11bGNyb3A7aD02MDtxPTEwMDt3PTQ2/https://s.yimg.com/xe/i/us/sp/v/nba_cutout/players_l/01072021/5142.png", "size": "small"}, "image_url": "https://s.yimg.com/iu/api/res/1.2/x4A6nosUX0Ueltqb9UXvRQ--~C/YXBwaWQ9eXNwb3J0cztjaD0yMzM2O2NyPTE7Y3c9MTc5MDtkeD04NTc7ZHk9MDtmaT11bGNyb3A7aD02MDtxPTEwMDt3PTQ2/https://s.yimg.com/xe/i/us/sp/v/nba_cutout/players_l/01072021/5142.png"}, {"is_undroppable": "0"}, {"position_type": "P"}, {"primary_position": "SG"}, {"eligible_positions": [{"position": "SG"}, {"position": "G"}, {"position": "SF"}, {"position": "F"}, {"position": "Util"}]}, {"has_player_notes": 1}, [], {"player_notes_last_timestamp": 1611525640}], {"selected_position": [{"coverage_type": "date", "date": "2021-01-27"}, {"position": "SG"}, {"is_flex": 0}]}]}, "2": {"player": [[{"player_key": "402.p.6065"}, {"player_id": "6065"}, {"name": {"full": "Shake Milton", "first": "Shake", "last": "Milton", "ascii_first": "Shake", "ascii_last": "Milton"}}, {"editorial_player_key": "nba.p.6065"}, {"editorial_team_key": "nba.t.20"}, {"editorial_team_full_name": "Philadelphia 76ers"}, {"editorial_team_abbr": "Phi"}, {"uniform_number": "18"}, {"display_position": "PG,SG"}, {"headshot": {"url": "https://s.yimg.com/iu/api/res/1.2/GTTySedNdfPcPxeyc8Z55w--~C/YXBwaWQ9eXNwb3J0cztjaD0yMzM2O2NyPTE7Y3c9MTc5MDtkeD04NTc7ZHk9MDtmaT11bGNyb3A7aD02MDtxPTEwMDt3PTQ2/https://s.yimg.com/xe/i/us/sp/v/nba_cutout/players_l/01082021/6065.png", "size": "small"}, "image_url": "https://s.yimg.com/iu/api/res/1.2/GTTySedNdfPcPxeyc8Z55w--~C/YXBwaWQ9eXNwb3J0cztjaD0yMzM2O2NyPTE7Y3c9MTc5MDtkeD04NTc7ZHk9MDtmaT11bGNyb3A7aD02MDtxPTEwMDt3PTQ2/https://s.yimg.com/xe/i/us/sp/v/nba_cutout/players_l/01082021/6065.png"}, {"is_undroppable": "0"}, {"position_type": "P"}, {"primary_position": "PG"}, {"eligible_positions": [{"position": "PG"}, {"position": "SG"}, {"position": "G"}, {"position": "Util"}]}, [], [], []], {"selected_position": [{"coverage_type": "date", "date": "2021-01-27"}, {"position": "G"}, {"is_flex": 0}]}]}, "3": {"player": [[{"player_key": "402.p.3704"}, {"player_id": "3704"}, {"name": {"full": "LeBron James", "first": "LeBron", "last": "James", "ascii_first": "LeBron", "ascii_last": "James"}}, {"editorial_player_key": "nba.p.3704"}, {"editorial_team_key": "nba.t.13"}, {"editorial_team_full_name": "Los Angeles Lakers"}, {"editorial_team_abbr": "LAL"}, {"uniform_number": "23"}, {"display_position": "PG,SG,SF"}, {"headshot": {"url": "https://s.yimg.com/iu/api/res/1.2/eAF.Tgg980pAAI70YAFECA--~C/YXBwaWQ9eXNwb3J0cztjaD0yMzM2O2NyPTE7Y3c9MTc5MDtkeD04NTc7ZHk9MDtmaT11bGNyb3A7aD02MDtxPTEwMDt3PTQ2/https://s.yimg.com/xe/i/us/sp/v/nba_cutout/players_l/01052021/3704.png", "size": "small"}, "image_url": "https://s.yimg.com/iu/api/res/1.2/eAF.Tgg980pAAI70YAFECA--~C/YXBwaWQ9eXNwb3J0cztjaD0yMzM2O2NyPTE7Y3c9MTc5MDtkeD04NTc7ZHk9MDtmaT11bGNyb3A7aD02MDtxPTEwMDt3PTQ2/https://s.yimg.com/xe/i/us/sp/v/nba_cutout/players_l/01052021/3704.png"}, {"is_undroppable": "1"}, {"position_type": "P"}, {"primary_position": "PG"}, {"eligible_positions": [{"position": "PG"}, {"position": "SG"}, {"position": "G"}, {"position": "SF"}, {"position": "F"}, {"position": "Util"}]}, {"has_player_notes": 1}, [], {"player_notes_last_timestamp": 1611633357}], {"selected_position": [{"coverage_type": "date", "date": "2021-01-27"}, {"position": "SF"}, {"is_flex": 0}]}]}, "4": {"player": [[{"player_key": "402.p.5894"}, {"player_id": "5894"}, {"name": {"full": "Chris Boucher", "first": "Chris", "last": "Boucher", "ascii_first": "Chris", "ascii_last": "Boucher"}}, {"editorial_player_key": "nba.p.5894"}, {"editorial_team_key": "nba.t.28"}, {"editorial_team_full_name": "Toronto Raptors"}, {"editorial_team_abbr": "Tor"}, {"uniform_number": "25"}, {"display_position": "PF,C"}, {"headshot": {"url": "https://s.yimg.com/iu/api/res/1.2/N12_Z_UKUeVVuNDABMYD8w--~C/YXBwaWQ9eXNwb3J0cztjaD0yMzM2O2NyPTE7Y3c9MTc5MDtkeD04NTc7ZHk9MDtmaT11bGNyb3A7aD02MDtxPTEwMDt3PTQ2/https://s.yimg.com/xe/i/us/sp/v/nba_cutout/players_l/01062021/5894.png", "size": "small"}, "image_url": "https://s.yimg.com/iu/api/res/1.2/N12_Z_UKUeVVuNDABMYD8w--~C/YXBwaWQ9eXNwb3J0cztjaD0yMzM2O2NyPTE7Y3c9MTc5MDtkeD04NTc7ZHk9MDtmaT11bGNyb3A7aD02MDtxPTEwMDt3PTQ2/https://s.yimg.com/xe/i/us/sp/v/nba_cutout/players_l/01062021/5894.png"}, {"is_undroppable": "0"}, {"position_type": "P"}, {"primary_position": "PF"}, {"eligible_positions": [{"position": "PF"}, {"position": "F"}, {"position": "C"}, {"position": "Util"}]}, {"has_player_notes": 1}, [], {"player_notes_last_timestamp": 1611630007}], {"selected_position": [{"coverage_type": "date", "date": "2021-01-27"}, {"position": "PF"}, {"is_flex": 0}]}]}, "5": {"player": [[{"player_key": "402.p.5014"}, {"player_id": "5014"}, {"name": {"full": "Terrence Ross", "first": "Terrence", "last": "Ross", "ascii_first": "Terrence", "ascii_last": "Ross"}}, {"editorial_player_key": "nba.p.5014"}, {"editorial_team_key": "nba.t.19"}, {"editorial_team_full_name": "Orlando Magic"}, {"editorial_team_abbr": "Orl"}, {"uniform_number": "31"}, {"display_position": "SG,SF"}, {"headshot": {"url": "https://s.yimg.com/iu/api/res/1.2/zaRimCUmWjfsScgPl1xW7g--~C/YXBwaWQ9eXNwb3J0cztjaD0yMzM2O2NyPTE7Y3c9MTc5MDtkeD04NTc7ZHk9MDtmaT11bGNyb3A7aD02MDtxPTEwMDt3PTQ2/https://s.yimg.com/xe/i/us/sp/v/nba_cutout/players_l/01112021/5014.png", "size": "small"}, "image_url": "https://s.yimg.com/iu/api/res/1.2/zaRimCUmWjfsScgPl1xW7g--~C/YXBwaWQ9eXNwb3J0cztjaD0yMzM2O2NyPTE7Y3c9MTc5MDtkeD04NTc7ZHk9MDtmaT11bGNyb3A7aD02MDtxPTEwMDt3PTQ2/https://s.yimg.com/xe/i/us/sp/v/nba_cutout/players_l/01112021/5014.png"}, {"is_undroppable": "0"}, {"position_type": "P"}, {"primary_position": "SG"}, {"eligible_positions": [{"position": "SG"}, {"position": "G"}, {"position": "SF"}, {"position": "F"}, {"position": "Util"}]}, [], [], []], {"selected_position": [{"coverage_type": "date", "date": "2021-01-27"}, {"position": "F"}, {"is_flex": 0}]}]}, "6": {"player": [[{"player_key": "402.p.5640"}, {"player_id": "5640"}, {"name": {"full": "Jakob Poeltl", "first": "Jakob", "last": "Poeltl", "ascii_first": "Jakob", "ascii_last": "Poeltl"}}, {"editorial_player_key": "nba.p.5640"}, {"editorial_team_key": "nba.t.24"}, {"editorial_team_full_name": "San Antonio Spurs"}, {"editorial_team_abbr": "SA"}, {"uniform_number": "25"}, {"display_position": "C"}, {"headshot": {"url": "https://s.yimg.com/iu/api/res/1.2/H54HqRJQz5g2m2z2JM6YxQ--~C/YXBwaWQ9eXNwb3J0cztjaD0yMzM2O2NyPTE7Y3c9MTc5MDtkeD04NTc7ZHk9MDtmaT11bGNyb3A7aD02MDtxPTEwMDt3PTQ2/https://s.yimg.com/xe/i/us/sp/v/nba_cutout/players_l/01112021/5640.png", "size": "small"}, "image_url": "https://s.yimg.com/iu/api/res/1.2/H54HqRJQz5g2m2z2JM6YxQ--~C/YXBwaWQ9eXNwb3J0cztjaD0yMzM2O2NyPTE7Y3c9MTc5MDtkeD04NTc7ZHk9MDtmaT11bGNyb3A7aD02MDtxPTEwMDt3PTQ2/https://s.yimg.com/xe/i/us/sp/v/nba_cutout/players_l/01112021/5640.png"}, {"is_undroppable": "0"}, {"position_type": "P"}, {"primary_position": "C"}, {"eligible_positions": [{"position": "C"}, {"position": "Util"}]}, {"has_player_notes": 1}, [], {"player_notes_last_timestamp": 1611376876}], {"selected_position": [{"coverage_type": "date", "date": "2021-01-27"}, {"position": "C"}, {"is_flex": 0}]}]}, "7": {"player": [[{"player_key": "402.p.4472"}, {"player_id": "4472"}, {"name": {"full": "Brook Lopez", "first": "Brook", "last": "Lopez", "ascii_first": "Brook", "ascii_last": "Lopez"}}, {"editorial_player_key": "nba.p.4472"}, {"editorial_team_key": "nba.t.15"}, {"editorial_team_full_name": "Milwaukee Bucks"}, {"editorial_team_abbr": "Mil"}, {"uniform_number": "11"}, {"display_position": "C"}, {"headshot": {"url": "https://s.yimg.com/iu/api/res/1.2/g8N6z2Hae3iU4ETuitGR1A--~C/YXBwaWQ9eXNwb3J0cztjaD0yMzM2O2NyPTE7Y3c9MTc5MDtkeD04NTc7ZHk9MDtmaT11bGNyb3A7aD02MDtxPTEwMDt3PTQ2/https://s.yimg.com/xe/i/us/sp/v/nba_cutout/players_l/12222020/4472.png", "size": "small"}, "image_url": "https://s.yimg.com/iu/api/res/1.2/g8N6z2Hae3iU4ETuitGR1A--~C/YXBwaWQ9eXNwb3J0cztjaD0yMzM2O2NyPTE7Y3c9MTc5MDtkeD04NTc7ZHk9MDtmaT11bGNyb3A7aD02MDtxPTEwMDt3PTQ2/https://s.yimg.com/xe/i/us/sp/v/nba_cutout/players_l/12222020/4472.png"}, {"is_undroppable": "0"}, {"position_type": "P"}, {"primary_position": "C"}, {"eligible_positions": [{"position": "C"}, {"position": "Util"}]}, {"has_player_notes": 1}, [], {"player_notes_last_timestamp": 1611546518}], {"selected_position": [{"coverage_type": "date", "date": "2021-01-27"}, {"position": "C"}, {"is_flex": 0}]}]}, "8": {"player": [[{"player_key": "402.p.4651"}, {"player_id": "4651"}, {"name": {"full": "Danny Green", "first": "Danny", "last": "Green", "ascii_first": "Danny", "ascii_last": "Green"}}, {"editorial_player_key": "nba.p.4651"}, {"editorial_team_key": "nba.t.20"}, {"editorial_team_full_name": "Philadelphia 76ers"}, {"editorial_team_abbr": "Phi"}, {"uniform_number": "14"}, {"display_position": "SG,SF"}, {"headshot": {"url": "https://s.yimg.com/iu/api/res/1.2/T8EdVJVX0gJJ80RXkj7jpg--~C/YXBwaWQ9eXNwb3J0cztjaD0yMzM2O2NyPTE7Y3c9MTc5MDtkeD04NTc7ZHk9MDtmaT11bGNyb3A7aD02MDtxPTEwMDt3PTQ2/https://s.yimg.com/xe/i/us/sp/v/nba_cutout/players_l/12142020/4651.png", "size": "small"}, "image_url": "https://s.yimg.com/iu/api/res/1.2/T8EdVJVX0gJJ80RXkj7jpg--~C/YXBwaWQ9eXNwb3J0cztjaD0yMzM2O2NyPTE7Y3c9MTc5MDtkeD04NTc7ZHk9MDtmaT11bGNyb3A7aD02MDtxPTEwMDt3PTQ2/https://s.yimg.com/xe/i/us/sp/v/nba_cutout/players_l/12142020/4651.png"}, {"is_undroppable": "0"}, {"position_type": "P"}, {"primary_position": "SG"}, {"eligible_positions": [{"position": "SG"}, {"position": "G"}, {"position": "SF"}, {"position": "F"}, {"position": "Util"}]}, {"has_player_notes": 1}, [], {"player_notes_last_timestamp": 1611204261}], {"selected_position": [{"coverage_type": "date", "date": "2021-01-27"}, {"position": "Util"}, {"is_flex": 0}]}]}, "9": {"player": [[{"player_key": "402.p.6073"}, {"player_id": "6073"}, {"name": {"full": "Duncan Robinson", "first": "Duncan", "last": "Robinson", "ascii_first": "Duncan", "ascii_last": "Robinson"}}, {"editorial_player_key": "nba.p.6073"}, {"editorial_team_key": "nba.t.14"}, {"editorial_team_full_name": "Miami Heat"}, {"editorial_team_abbr": "Mia"}, {"uniform_number": "55"}, {"display_position": "SG,SF"}, {"headshot": {"url": "https://s.yimg.com/iu/api/res/1.2/rTx7viPyAwtdKoJIIFVwOg--~C/YXBwaWQ9eXNwb3J0cztjaD0yMzM2O2NyPTE7Y3c9MTc5MDtkeD04NTc7ZHk9MDtmaT11bGNyb3A7aD02MDtxPTEwMDt3PTQ2/https://s.yimg.com/xe/i/us/sp/v/nba_cutout/players_l/01082021/6073.png", "size": "small"}, "image_url": "https://s.yimg.com/iu/api/res/1.2/rTx7viPyAwtdKoJIIFVwOg--~C/YXBwaWQ9eXNwb3J0cztjaD0yMzM2O2NyPTE7Y3c9MTc5MDtkeD04NTc7ZHk9MDtmaT11bGNyb3A7aD02MDtxPTEwMDt3PTQ2/https://s.yimg.com/xe/i/us/sp/v/nba_cutout/players_l/01082021/6073.png"}, {"is_undroppable": "0"}, {"position_type": "P"}, {"primary_position": "SG"}, {"eligible_positions": [{"position": "SG"}, {"position": "G"}, {"position": "SF"}, {"position": "F"}, {"position": "Util"}]}, {"has_player_notes": 1}, [], {"player_notes_last_timestamp": 1611206930}], {"selected_position": [{"coverage_type": "date", "date": "2021-01-27"}, {"position": "Util"}, {"is_flex": 0}]}]}, "10": {"player": [[{"player_key": "402.p.5321"}, {"player_id": "5321"}, {"name": {"full": "Elfrid Payton", "first": "Elfrid", "last": "Payton", "ascii_first": "Elfrid", "ascii_last": "Payton"}}, {"editorial_player_key": "nba.p.5321"}, {"editorial_team_key": "nba.t.18"}, {"editorial_team_full_name": "New York Knicks"}, {"editorial_team_abbr": "NY"}, {"uniform_number": "6"}, {"display_position": "PG"}, {"headshot": {"url": "https://s.yimg.com/iu/api/res/1.2/KCPh_ZuOyvywSOIAfdFtBQ--~C/YXBwaWQ9eXNwb3J0cztjaD0yMzM2O2NyPTE7Y3c9MTc5MDtkeD04NTc7ZHk9MDtmaT11bGNyb3A7aD02MDtxPTEwMDt3PTQ2/https://s.yimg.com/xe/i/us/sp/v/nba_cutout/players_l/01112021/5321.png", "size": "small"}, "image_url": "https://s.yimg.com/iu/api/res/1.2/KCPh_ZuOyvywSOIAfdFtBQ--~C/YXBwaWQ9eXNwb3J0cztjaD0yMzM2O2NyPTE7Y3c9MTc5MDtkeD04NTc7ZHk9MDtmaT11bGNyb3A7aD02MDtxPTEwMDt3PTQ2/https://s.yimg.com/xe/i/us/sp/v/nba_cutout/players_l/01112021/5321.png"}, {"is_undroppable": "0"}, {"position_type": "P"}, {"primary_position": "PG"}, {"eligible_positions": [{"position": "PG"}, {"position": "G"}, {"position": "Util"}]}, {"has_player_notes": 1}, [], {"player_notes_last_timestamp": 1611077464}], {"selected_position": [{"coverage_type": "date", "date": "2021-01-27"}, {"position": "BN"}, {"is_flex": 0}]}]}, "11": {"player": [[{"player_key": "402.p.4486"}, {"player_id": "4486"}, {"name": {"full": "Serge Ibaka", "first": "Serge", "last": "Ibaka", "ascii_first": "Serge", "ascii_last": "Ibaka"}}, {"editorial_player_key": "nba.p.4486"}, {"editorial_team_key": "nba.t.12"}, {"editorial_team_full_name": "Los Angeles Clippers"}, {"editorial_team_abbr": "LAC"}, {"uniform_number": "9"}, {"display_position": "PF,C"}, {"headshot": {"url": "https://s.yimg.com/iu/api/res/1.2/ri9U2T3KqRJoF_aV7nJ4Jw--~C/YXBwaWQ9eXNwb3J0cztjaD0yMzM2O2NyPTE7Y3c9MTc5MDtkeD04NTc7ZHk9MDtmaT11bGNyb3A7aD02MDtxPTEwMDt3PTQ2/https://s.yimg.com/xe/i/us/sp/v/nba_cutout/players_l/12142020/4486.png", "size": "small"}, "image_url": "https://s.yimg.com/iu/api/res/1.2/ri9U2T3KqRJoF_aV7nJ4Jw--~C/YXBwaWQ9eXNwb3J0cztjaD0yMzM2O2NyPTE7Y3c9MTc5MDtkeD04NTc7ZHk9MDtmaT11bGNyb3A7aD02MDtxPTEwMDt3PTQ2/https://s.yimg.com/xe/i/us/sp/v/nba_cutout/players_l/12142020/4486.png"}, {"is_undroppable": "0"}, {"position_type": "P"}, {"primary_position": "PF"}, {"eligible_positions": [{"position": "PF"}, {"position": "F"}, {"position": "C"}, {"position": "Util"}]}, {"has_player_notes": 1}, [], {"player_notes_last_timestamp": 1611197226}], {"selected_position": [{"coverage_type": "date", "date": "2021-01-27"}, {"position": "BN"}, {"is_flex": 0}]}]}, "12": {"player": [[{"player_key": "402.p.3706"}, {"player_id": "3706"}, {"name": {"full": "Carmelo Anthony", "first": "Carmelo", "last": "Anthony", "ascii_first": "Carmelo", "ascii_last": "Anthony"}}, {"editorial_player_key": "nba.p.3706"}, {"editorial_team_key": "nba.t.22"}, {"editorial_team_full_name": "Portland Trail Blazers"}, {"editorial_team_abbr": "Por"}, {"uniform_number": "00"}, {"display_position": "SF,PF"}, {"headshot": {"url": "https://s.yimg.com/iu/api/res/1.2/au.5MykIhcvUkG.FhIAfdA--~C/YXBwaWQ9eXNwb3J0cztjaD0yMzM2O2NyPTE7Y3c9MTc5MDtkeD04NTc7ZHk9MDtmaT11bGNyb3A7aD02MDtxPTEwMDt3PTQ2/https://s.yimg.com/xe/i/us/sp/v/nba_cutout/players_l/12182020/3706.png", "size": "small"}, "image_url": "https://s.yimg.com/iu/api/res/1.2/au.5MykIhcvUkG.FhIAfdA--~C/YXBwaWQ9eXNwb3J0cztjaD0yMzM2O2NyPTE7Y3c9MTc5MDtkeD04NTc7ZHk9MDtmaT11bGNyb3A7aD02MDtxPTEwMDt3PTQ2/https://s.yimg.com/xe/i/us/sp/v/nba_cutout/players_l/12182020/3706.png"}, {"is_undroppable": "0"}, {"position_type": "P"}, {"primary_position": "SF"}, {"eligible_positions": [{"position": "SF"}, {"position": "PF"}, {"position": "F"}, {"position": "Util"}]}, {"has_player_notes": 1}, [], {"player_notes_last_timestamp": 1611640186}], {"selected_position": [{"coverage_type": "date", "date": "2021-01-27"}, {"position": "BN"}, {"is_flex": 0}]}]}, "13": {"player": [[{"player_key": "402.p.4896"}, {"player_id": "4896"}, {"name": {"full": "Kawhi Leonard", "first": "Kawhi", "last": "Leonard", "ascii_first": "Kawhi", "ascii_last": "Leonard"}}, {"status": "INJ", "status_full": "Injured (IL-eligible)"}, {"injury_note": "Covid-19"}, {"editorial_player_key": "nba.p.4896"}, {"editorial_team_key": "nba.t.12"}, {"editorial_team_full_name": "Los Angeles Clippers"}, {"editorial_team_abbr": "LAC"}, {"uniform_number": "2"}, {"display_position": "SG,SF"}, {"headshot": {"url": "https://s.yimg.com/iu/api/res/1.2/oaY5.0HqtrP9qUd81jNO1w--~C/YXBwaWQ9eXNwb3J0cztjaD0yMzM2O2NyPTE7Y3c9MTc5MDtkeD04NTc7ZHk9MDtmaT11bGNyb3A7aD02MDtxPTEwMDt3PTQ2/https://s.yimg.com/xe/i/us/sp/v/nba_cutout/players_l/01052021/4896.png", "size": "small"}, "image_url": "https://s.yimg.com/iu/api/res/1.2/oaY5.0HqtrP9qUd81jNO1w--~C/YXBwaWQ9eXNwb3J0cztjaD0yMzM2O2NyPTE7Y3c9MTc5MDtkeD04NTc7ZHk9MDtmaT11bGNyb3A7aD02MDtxPTEwMDt3PTQ2/https://s.yimg.com/xe/i/us/sp/v/nba_cutout/players_l/01052021/4896.png"}, {"is_undroppable": "1"}, {"position_type": "P"}, {"primary_position": "SG"}, {"eligible_positions": [{"position": "SG"}, {"position": "G"}, {"position": "SF"}, {"position": "F"}, {"position": "Util"}, {"position": "IL"}]}, {"has_player_notes": 1}, [], {"player_notes_last_timestamp": 1611613228}], {"selected_position": [{"coverage_type": "date", "date": "2021-01-27"}, {"position": "IL"}, {"is_flex": 0}]}]}, "count": 14}}}}], "time": "53.310871124268ms", "copyright": "Data provided by Yahoo! and STATS, LLC", "refresh_rate": "60"}}