[{"stat": {"stat_id": "9004003", "value": "186/420"}}, {"stat": {"stat_id": "5", "value": ".443"}}, {"stat": {"stat_id": "9007006", "value": "58/90"}}, {"stat": {"stat_id": "8", "value": ".644"}}, {"stat": {"stat_id": "10", "value": "60"}}, {"stat": {"stat_id": "12", "value": "490"}}, {"stat": {"stat_id": "15", "value": "244"}}, {"stat": {"stat_id": "16", "value": "139"}}, {"stat": {"stat_id": "17", "value": "37"}}, {"stat": {"stat_id": "18", "value": "37"}}, {"stat": {"stat_id": "19", "value": "62"}}]